[
    {
        "id": "2179825c-e325-4f5c-9715-a626845a1bbd",
        "build_id": "6a3f88e0-5fe7-4eee-a94b-cacf9e7d0e39",
        "round_number": 1,
        "cash_earned": 0,
        "created_at": "2025-06-25T00:36:27.056476+00:00",
        "notes": "Not much choice here round 1. Get the small weapon buffs, play smart since your DPS is the best part of your kit.",
        "stats": {
            "LIFE": 75,
            "Armor": 0,
            "Shield": 175,
            "Max Ammo": 0,
            "Move Speed": 0,
            "Total LIFE": 256,
            "Attack Speed": 5,
            "Weapon Power": 5,
            "Ability Power": 0,
            "Critical Damage": 0,
            "Weapon Lifesteal": 10,
            "Ability Lifesteal": 0,
            "Cooldown Reduction": 0
        },
        "round_upgrades": [
            {
                "id": "d140d0f3-f4b4-40ff-a322-aa33bdd98c6f",
                "notes": "",
                "action": "buy",
                "upgrade_id": "2a354f80-610c-4661-9bdd-8960ae1a60b0"
            },
            {
                "id": "38ae66d2-e78b-425c-8881-45b9b9b04267",
                "notes": "",
                "action": "buy",
                "upgrade_id": "25869f9a-9a29-4e19-96b6-9d8a28c59318"
            },
            {
                "id": "864de143-6216-4943-9a3a-797b95387a0b",
                "notes": "",
                "action": "buy",
                "upgrade_id": "961ae72f-434f-406b-a89b-ab8efec806bf"
            },
            {
                "id": "9607a954-de49-41d6-a150-ae2ef38e3173",
                "notes": "",
                "action": "buy",
                "upgrade_id": "da870e1e-7d1b-4170-b172-1be1485c0c56"
            }
        ]
    },
    {
        "id": "c3707b15-2772-499d-8f88-fcd2f43c071f",
        "build_id": "6a3f88e0-5fe7-4eee-a94b-cacf9e7d0e39",
        "round_number": 2,
        "cash_earned": 0,
        "created_at": "2025-06-25T00:36:27.056476+00:00",
        "notes": "Provided you played well round 1, you should be able to afford some attack speed buffs. Don't need to overthink it. This should be where you start to notice your charged right clicks begin to one tap squishies on good aim.",
        "stats": {
            "LIFE": 100,
            "Armor": 0,
            "Shield": 175,
            "Max Ammo": 0,
            "Move Speed": 5,
            "Total LIFE": 275,
            "Attack Speed": 15,
            "Weapon Power": 20,
            "Ability Power": 0,
            "Critical Damage": 0,
            "Weapon Lifesteal": 10,
            "Ability Lifesteal": 0,
            "Cooldown Reduction": 0
        },
        "round_upgrades": [
            {
                "id": "1e4078c1-0133-4a89-9e65-53dd9d3c5893",
                "notes": "",
                "action": "buy",
                "upgrade_id": "da870e1e-7d1b-4170-b172-1be1485c0c56"
            },
            {
                "id": "a1d89ca5-7f2c-4083-bbcc-68c50cd5e140",
                "notes": "",
                "action": "buy",
                "upgrade_id": "c0ca1795-a3ea-4dc9-ae17-f34122574b3a"
            },
            {
                "id": "4f1bdd2f-ee94-4bb4-807c-4b430332e696",
                "notes": "",
                "action": "buy",
                "upgrade_id": "2485b212-b286-42d0-a2bd-20eb4396b054"
            },
            {
                "id": "52ae15b3-d4c9-4550-ad53-7a01b557c84b",
                "notes": "",
                "action": "buy",
                "upgrade_id": "2a354f80-610c-4661-9bdd-8960ae1a60b0"
            },
            {
                "id": "22ba345b-f5d3-4e36-9e5f-d18f7d572007",
                "notes": "",
                "action": "buy",
                "upgrade_id": "25869f9a-9a29-4e19-96b6-9d8a28c59318"
            },
            {
                "id": "3b33147c-6298-488c-b4c3-c752bed342ec",
                "notes": "",
                "action": "buy",
                "upgrade_id": "961ae72f-434f-406b-a89b-ab8efec806bf"
            }
        ]
    },
    {
        "id": "2f163b35-b748-4d19-95c2-2fd8b5974393",
        "build_id": "6a3f88e0-5fe7-4eee-a94b-cacf9e7d0e39",
        "round_number": 3,
        "cash_earned": 0,
        "created_at": "2025-06-25T00:36:27.056476+00:00",
        "notes": "Round 3 is critical for this build, as Seeking Salvation is an ability that makes your charged shots home in on low health enemies. Pair with the faster charge-up ability (Genji's Galvanic Gloves), and you should be able to rip off kill after kill on flankers and backline, particularly Anas, Reapers, and Kirikos. This is a great way to farm money and claim bounties.",
        "stats": {
            "LIFE": 124,
            "Armor": 0,
            "Shield": 175,
            "Max Ammo": 0,
            "Move Speed": 5,
            "Total LIFE": 299,
            "Attack Speed": 25,
            "Weapon Power": 30,
            "Ability Power": 0,
            "Critical Damage": 0,
            "Weapon Lifesteal": 10,
            "Ability Lifesteal": 0,
            "Cooldown Reduction": 0
        },
        "round_upgrades": [
            {
                "id": "6ac74f35-35cb-453e-afa1-49be753c223f",
                "notes": "",
                "action": "buy",
                "upgrade_id": "2a354f80-610c-4661-9bdd-8960ae1a60b0"
            },
            {
                "id": "fbae3e2c-7e42-4011-99ed-bc65c76562eb",
                "notes": "",
                "action": "buy",
                "upgrade_id": "25869f9a-9a29-4e19-96b6-9d8a28c59318"
            },
            {
                "id": "edd24181-e9c2-4896-b5c2-f98c42c25495",
                "notes": "",
                "action": "buy",
                "upgrade_id": "961ae72f-434f-406b-a89b-ab8efec806bf"
            },
            {
                "id": "b68b2eb2-e869-4e59-822a-10af5fc0eb19",
                "notes": "",
                "action": "buy",
                "upgrade_id": "c0ca1795-a3ea-4dc9-ae17-f34122574b3a"
            },
            {
                "id": "92c46d21-8b88-4508-b829-3812eb5f8f36",
                "notes": "",
                "action": "buy",
                "upgrade_id": "2485b212-b286-42d0-a2bd-20eb4396b054"
            },
            {
                "id": "e680ea92-2ad1-4dff-bdd6-b1d56e8be61a",
                "notes": "",
                "action": "buy",
                "upgrade_id": "f633cda1-b736-4071-9221-402af4ac7a43"
            },
            {
                "id": "63919aca-4fc7-46ff-8352-df4d113e5fb0",
                "notes": "",
                "action": "buy",
                "upgrade_id": "da870e1e-7d1b-4170-b172-1be1485c0c56"
            },
            {
                "id": "260bc0db-1abd-480e-b47e-72a6731f66d9",
                "notes": "",
                "action": "buy",
                "upgrade_id": "c424d9c0-3a6e-4eb6-b845-cfa284481307"
            }
        ]
    },
    {
        "id": "0f83b8cc-67fa-4ab0-82b4-3f38dbd6fc15",
        "build_id": "6a3f88e0-5fe7-4eee-a94b-cacf9e7d0e39",
        "round_number": 4,
        "cash_earned": 0,
        "created_at": "2025-06-25T00:36:27.056476+00:00",
        "notes": "Round 4 you have some flexibility. I prefer to boost the attack speed by 20% here, as it makes left clicking significantly more powerful for situations where it makes sense, especially when paired with discord orb. If you prefer to swap in damage upgrades here that works too, but typically in close games getting in that one extra shot matters more than marginally more damage, especially with Zen's headshot damage already being so high.",
        "stats": {
            "LIFE": 142,
            "Armor": 0,
            "Shield": 175,
            "Max Ammo": 0,
            "Move Speed": 5,
            "Total LIFE": 317,
            "Attack Speed": 40,
            "Weapon Power": 30,
            "Ability Power": 0,
            "Critical Damage": 0,
            "Weapon Lifesteal": 0,
            "Ability Lifesteal": 0,
            "Cooldown Reduction": 0
        },
        "round_upgrades": [
            {
                "id": "f6b9428b-92a3-4ae2-a557-385581aab81b",
                "notes": "",
                "action": "buy",
                "upgrade_id": "da870e1e-7d1b-4170-b172-1be1485c0c56"
            },
            {
                "id": "d510715b-bfaa-476b-890f-7ae6af42d283",
                "notes": "",
                "action": "buy",
                "upgrade_id": "c424d9c0-3a6e-4eb6-b845-cfa284481307"
            },
            {
                "id": "f6704956-d503-49c3-91ab-cf71f5e8c9a3",
                "notes": "",
                "action": "optional",
                "upgrade_id": "25869f9a-9a29-4e19-96b6-9d8a28c59318"
            },
            {
                "id": "24d5c5ec-5535-4ea2-847f-47f08ea1103f",
                "notes": "",
                "action": "optional",
                "upgrade_id": "961ae72f-434f-406b-a89b-ab8efec806bf"
            },
            {
                "id": "41697b76-edba-4761-9182-fb2572cf708b",
                "notes": "",
                "action": "optional",
                "upgrade_id": "be06e8c1-baa4-4c24-ae40-c103c45ea0c3"
            },
            {
                "id": "bb38f9ba-8483-4768-92a9-7d59bdc0301b",
                "notes": "",
                "action": "buy",
                "upgrade_id": "a291de85-b6d9-43cf-b5da-f3184a156f48"
            },
            {
                "id": "85f0b8bb-2570-4804-a8eb-cc74fd4f1358",
                "notes": "",
                "action": "buy",
                "upgrade_id": "2a354f80-610c-4661-9bdd-8960ae1a60b0"
            },
            {
                "id": "27c4ddff-0205-48bf-af1f-e487298c0365",
                "notes": "",
                "action": "buy",
                "upgrade_id": "c0ca1795-a3ea-4dc9-ae17-f34122574b3a"
            },
            {
                "id": "465b3391-6952-4b99-87fa-b0a8fddf72be",
                "notes": "",
                "action": "buy",
                "upgrade_id": "2485b212-b286-42d0-a2bd-20eb4396b054"
            },
            {
                "id": "a817a785-f2a1-4468-a24c-d969a59c20ca",
                "notes": "",
                "action": "buy",
                "upgrade_id": "f633cda1-b736-4071-9221-402af4ac7a43"
            }
        ]
    },
    {
        "id": "b4a91a6b-d87f-44c6-9963-44634a53e9ae",
        "build_id": "6a3f88e0-5fe7-4eee-a94b-cacf9e7d0e39",
        "round_number": 5,
        "cash_earned": 0,
        "created_at": "2025-06-25T00:36:27.056476+00:00",
        "notes": "Round 5 your power should always be the harmony orb buff. You should be putting out thousands in damage per round, so applying a damage-related healing buff to your harmony orb only makes sense. This should allow you to farm your ultimate extremely quickly, which saves your team sometimes as soon as the first team fight. Quick ults are a great way to print income to quickly ramp up your potency.",
        "stats": {
            "LIFE": 161,
            "Armor": 0,
            "Shield": 175,
            "Max Ammo": 0,
            "Move Speed": 5,
            "Total LIFE": 336,
            "Attack Speed": 50,
            "Weapon Power": 30,
            "Ability Power": 0,
            "Critical Damage": 0,
            "Weapon Lifesteal": 0,
            "Ability Lifesteal": 0,
            "Cooldown Reduction": 0
        },
        "round_upgrades": [
            {
                "id": "05e78511-1fba-41f9-98be-c8c439d46e62",
                "notes": "",
                "action": "buy",
                "upgrade_id": "2a354f80-610c-4661-9bdd-8960ae1a60b0"
            },
            {
                "id": "76ec8f5e-c087-4c50-845d-4b546d67770a",
                "notes": "",
                "action": "buy",
                "upgrade_id": "c0ca1795-a3ea-4dc9-ae17-f34122574b3a"
            },
            {
                "id": "ff7b3337-dbc2-4969-823f-2e1fcbaeac0b",
                "notes": "",
                "action": "buy",
                "upgrade_id": "2485b212-b286-42d0-a2bd-20eb4396b054"
            },
            {
                "id": "33686048-4fbf-427c-9753-7e006a0f123b",
                "notes": "",
                "action": "buy",
                "upgrade_id": "f633cda1-b736-4071-9221-402af4ac7a43"
            },
            {
                "id": "a025d3d8-b3cf-431f-bf16-c24f7ad89851",
                "notes": "",
                "action": "buy",
                "upgrade_id": "a291de85-b6d9-43cf-b5da-f3184a156f48"
            },
            {
                "id": "bf885e3b-c1d9-48b4-ad99-37f654edb0f0",
                "notes": "",
                "action": "buy",
                "upgrade_id": "396c0970-daa8-47e3-8049-e65f03fe5cec"
            },
            {
                "id": "65f08bbb-09f2-468d-aabd-c573eedac2df",
                "notes": "",
                "action": "buy",
                "upgrade_id": "da870e1e-7d1b-4170-b172-1be1485c0c56"
            },
            {
                "id": "baff6e92-43f0-4ead-8389-c2d1ef310f49",
                "notes": "",
                "action": "buy",
                "upgrade_id": "c424d9c0-3a6e-4eb6-b845-cfa284481307"
            },
            {
                "id": "3408582b-e3fd-4655-adf6-ba17f5cc809e",
                "notes": "",
                "action": "buy",
                "upgrade_id": "8392e752-ca6b-487d-9580-11eab6075c3c"
            }
        ]
    },
    {
        "id": "ed8ad2ba-98ce-4740-935d-37e5a684c272",
        "build_id": "6a3f88e0-5fe7-4eee-a94b-cacf9e7d0e39",
        "round_number": 6,
        "cash_earned": 0,
        "created_at": "2025-06-25T00:36:27.056476+00:00",
        "notes": "I prefer to take the weapon damage boost here, particularly the one that ignores armor reduction. If you've made it to round 6 you're likely struggling with a high mobility tank like Rein, Orisa or DVA targeting you. With this buff, you should be able to shred them or bring them to the brink of death with a discord orb/full charge burst. This can be swapped out for other upgrades if the enemy tank isn't playing aggressively towards you, such as the Barrier Damage boost for Rein and Sigma (sometimes Orisa) counterplay, as well as some survivability like Martian Mender if you find you're getting poked to death.",
        "stats": {
            "LIFE": 177,
            "Armor": 0,
            "Shield": 175,
            "Max Ammo": 0,
            "Move Speed": 5,
            "Total LIFE": 352,
            "Attack Speed": 50,
            "Weapon Power": 40,
            "Ability Power": 0,
            "Critical Damage": 0,
            "Weapon Lifesteal": 0,
            "Ability Lifesteal": 0,
            "Cooldown Reduction": 0
        },
        "round_upgrades": [
            {
                "id": "74669af9-5b33-43ce-bd84-425ced3019be",
                "notes": "",
                "action": "buy",
                "upgrade_id": "da870e1e-7d1b-4170-b172-1be1485c0c56"
            },
            {
                "id": "8868fd9c-fd4a-472e-9db8-a85698e61be8",
                "notes": "",
                "action": "buy",
                "upgrade_id": "c424d9c0-3a6e-4eb6-b845-cfa284481307"
            },
            {
                "id": "2883a028-8d95-40d6-ab12-2c64d76a9177",
                "notes": "",
                "action": "buy",
                "upgrade_id": "8392e752-ca6b-487d-9580-11eab6075c3c"
            },
            {
                "id": "63c7e90c-af2e-4c53-84ba-c4da8f641830",
                "notes": "",
                "action": "optional",
                "upgrade_id": "2a354f80-610c-4661-9bdd-8960ae1a60b0"
            },
            {
                "id": "0cedff44-ef13-499e-ad1c-b94dd1513ac2",
                "notes": "",
                "action": "buy",
                "upgrade_id": "caa96c7e-655f-4d03-9bd9-0f41937fec27"
            },
            {
                "id": "0d88ad88-da31-4172-a13b-4b987c2a3370",
                "notes": "",
                "action": "buy",
                "upgrade_id": "c0ca1795-a3ea-4dc9-ae17-f34122574b3a"
            },
            {
                "id": "f168a67d-eaa3-4434-a687-1c2cb76b08e7",
                "notes": "",
                "action": "buy",
                "upgrade_id": "2485b212-b286-42d0-a2bd-20eb4396b054"
            },
            {
                "id": "d8a8d2ae-fe88-4e0a-8533-4d9f282527f9",
                "notes": "",
                "action": "buy",
                "upgrade_id": "f633cda1-b736-4071-9221-402af4ac7a43"
            },
            {
                "id": "b8ee8483-95ce-4d7e-9ed9-1ad824bf5659",
                "notes": "",
                "action": "buy",
                "upgrade_id": "a291de85-b6d9-43cf-b5da-f3184a156f48"
            },
            {
                "id": "2b20b71c-215d-4df4-80ee-3b2bd3239bcc",
                "notes": "",
                "action": "buy",
                "upgrade_id": "396c0970-daa8-47e3-8049-e65f03fe5cec"
            }
        ]
    },
    {
        "id": "4c33c3b8-4b73-441b-927f-3e5ac923ab81",
        "build_id": "6a3f88e0-5fe7-4eee-a94b-cacf9e7d0e39",
        "round_number": 7,
        "cash_earned": 0,
        "created_at": "2025-06-25T00:36:27.056476+00:00",
        "notes": "If you've made it to round 7, the best choice here is to grab the Instant Karma power. This allows you to peek for a moment longer and really make sure you hit your shots, as the self heal may buy you an extra second around a corner. Overall, you have a lot of flexibility at this point, since you should have some excess cash provided you're carrying your team. I personally highly reccommend either more attack speed, or more weapon damage. Ability power is cool, but you should be able to get ults ridiculously fast from your ridiculous burst damage.",
        "stats": {
            "LIFE": 200,
            "Armor": 0,
            "Shield": 175,
            "Max Ammo": 0,
            "Move Speed": 0,
            "Total LIFE": 375,
            "Attack Speed": 55,
            "Weapon Power": 35,
            "Ability Power": 0,
            "Critical Damage": 0,
            "Weapon Lifesteal": 0,
            "Ability Lifesteal": 0,
            "Cooldown Reduction": 0
        },
        "round_upgrades": [
            {
                "id": "069fb468-8589-4f05-aeea-ba8ce416841c",
                "notes": "",
                "action": "optional",
                "upgrade_id": "c0ca1795-a3ea-4dc9-ae17-f34122574b3a"
            },
            {
                "id": "b7ef9eef-338c-41e0-b145-c73b436b847f",
                "notes": "",
                "action": "optional",
                "upgrade_id": "2485b212-b286-42d0-a2bd-20eb4396b054"
            },
            {
                "id": "b6c23595-7ead-4c1a-89b0-5c2a7a63ecd7",
                "notes": "",
                "action": "buy",
                "upgrade_id": "f633cda1-b736-4071-9221-402af4ac7a43"
            },
            {
                "id": "d276a011-b8a3-4b63-95f1-a898e50ba131",
                "notes": "",
                "action": "buy",
                "upgrade_id": "a291de85-b6d9-43cf-b5da-f3184a156f48"
            },
            {
                "id": "1372e799-978a-4399-9f29-388e4f87d01e",
                "notes": "",
                "action": "buy",
                "upgrade_id": "396c0970-daa8-47e3-8049-e65f03fe5cec"
            },
            {
                "id": "3ec330b1-1bff-4db8-ac35-f8c897179898",
                "notes": "",
                "action": "buy",
                "upgrade_id": "caa96c7e-655f-4d03-9bd9-0f41937fec27"
            },
            {
                "id": "509fd6de-d7c6-4bbf-be51-4ecf38a182d4",
                "notes": "",
                "action": "buy",
                "upgrade_id": "72386db6-753e-413d-aa2a-f1389842f47f"
            },
            {
                "id": "de687934-c77d-4fa0-9c4b-b1c681e66255",
                "notes": "",
                "action": "buy",
                "upgrade_id": "be06e8c1-baa4-4c24-ae40-c103c45ea0c3"
            },
            {
                "id": "ac46549a-edfd-43f9-a551-88fa917a5f6e",
                "notes": "",
                "action": "buy",
                "upgrade_id": "da870e1e-7d1b-4170-b172-1be1485c0c56"
            },
            {
                "id": "c79e2da5-ab39-4022-95b8-7e85b2f3b0b4",
                "notes": "",
                "action": "buy",
                "upgrade_id": "c424d9c0-3a6e-4eb6-b845-cfa284481307"
            },
            {
                "id": "1cd39f6a-d55c-441f-969f-0d1fd6bf1d26",
                "notes": "",
                "action": "buy",
                "upgrade_id": "8392e752-ca6b-487d-9580-11eab6075c3c"
            },
            {
                "id": "42230ace-1c12-4ea3-b056-ab291bc824b8",
                "notes": "",
                "action": "buy",
                "upgrade_id": "7a1cb409-3f6d-424f-882f-729c59476130"
            }
        ]
    }
]